mattermostautodriver/__init__.py
mattermostautodriver/client.py
mattermostautodriver/exceptions.py
mattermostautodriver/version.py
mattermostautodriver/websocket.py
mattermostautodriver/driver/__init__.py
mattermostautodriver/driver/base.py
mattermostautodriver/driver/driver.py
mattermostautodriver/driver/endpoint_base.py
mattermostautodriver/endpoints/__init__.py
mattermostautodriver/endpoints/_base.py
mattermostautodriver/endpoints/access_control.py
mattermostautodriver/endpoints/agents.py
mattermostautodriver/endpoints/audit_logs.py
mattermostautodriver/endpoints/authentication.py
mattermostautodriver/endpoints/bleve.py
mattermostautodriver/endpoints/bookmarks.py
mattermostautodriver/endpoints/bots.py
mattermostautodriver/endpoints/brand.py
mattermostautodriver/endpoints/channels.py
mattermostautodriver/endpoints/cloud.py
mattermostautodriver/endpoints/cluster.py
mattermostautodriver/endpoints/commands.py
mattermostautodriver/endpoints/compliance.py
mattermostautodriver/endpoints/conditions.py
mattermostautodriver/endpoints/custom_profile_attributes.py
mattermostautodriver/endpoints/data_retention.py
mattermostautodriver/endpoints/elasticsearch.py
mattermostautodriver/endpoints/emoji.py
mattermostautodriver/endpoints/exports.py
mattermostautodriver/endpoints/files.py
mattermostautodriver/endpoints/filtering.py
mattermostautodriver/endpoints/group_message.py
mattermostautodriver/endpoints/groups.py
mattermostautodriver/endpoints/imports.py
mattermostautodriver/endpoints/integration_actions.py
mattermostautodriver/endpoints/internal.py
mattermostautodriver/endpoints/ip.py
mattermostautodriver/endpoints/jobs.py
mattermostautodriver/endpoints/ldap.py
mattermostautodriver/endpoints/logs.py
mattermostautodriver/endpoints/metrics.py
mattermostautodriver/endpoints/migrate.py
mattermostautodriver/endpoints/o_auth.py
mattermostautodriver/endpoints/oauth.py
mattermostautodriver/endpoints/outgoing_connections.py
mattermostautodriver/endpoints/outgoing_oauth_connections.py
mattermostautodriver-11.3.0.dist-info/licenses/LICENSE
mattermostautodriver-11.3.0.dist-info/METADATA
mattermostautodriver-11.3.0.dist-info/WHEEL
mattermostautodriver-11.3.0.dist-info/top_level.txt
mattermostautodriver-11.3.0.dist-info/RECORD
