Metadata-Version: 2.4
Name: mattermostautodriver
Version: 11.3.0
Summary: A Python Mattermost Auto Driver
Home-page: https://github.com/embl-bio-it/python-mattermost-autodriver
Author: Renato Alves, Christian Plümer
Author-email: bio-it@embl.de, github@kuuku.net
License: MIT
Classifier: Development Status :: 5 - Production/Stable
Classifier: Environment :: Web Environment
Classifier: Intended Audience :: Developers
Classifier: Programming Language :: Python
Classifier: Programming Language :: Python :: 3
Classifier: Programming Language :: Python :: 3.10
Classifier: Programming Language :: Python :: 3.11
Classifier: Programming Language :: Python :: 3.12
Classifier: Programming Language :: Python :: 3.13
Requires-Python: >=3.10
License-File: LICENSE
Requires-Dist: aiohttp<4.0.0,>=3.9.5
Requires-Dist: httpx~=0.28.1
Dynamic: author
Dynamic: author-email
Dynamic: classifier
Dynamic: description
Dynamic: home-page
Dynamic: license
Dynamic: license-file
Dynamic: requires-dist
Dynamic: requires-python
Dynamic: summary
